{
  "notify_url": "http://localhost:8090/trackupload",
  "analysis_node": "7d4f2f62-0f7e-4a80-882c-08fa65e700f0",
  "face_src": 8,
  "car_src": 8,
  "mix_src": 0,
  "face_urls": [
    "file:///extdata/videos/hf/bhs_1.mp4",
    "file:///extdata/videos/hf/bhs_2.mp4",
    "file:///extdata/videos/hf/hhl_1.mp4",
    "file:///extdata/videos/hf/hhl_2.mp4",
    "file:///extdata/videos/hf/jxl_1.mp4",
    "file:///extdata/videos/hf/jxl_2.mp4"
  ],
  "car_urls": [
    "rtsp://192.168.1.26/xcz.264",
    "rtsp://192.168.1.26/qxl1.264",
    "rtsp://192.168.1.26/gd1.264",
    "rtsp://192.168.1.26/bm/car_1.264",
    "rtsp://192.168.1.26/bm/car_2.264",
    "rtsp://192.168.1.26/bm/car_3.264",
    "rtsp://192.168.1.26/bm/car_4.264",
    "rtsp://192.168.1.26/bm/car_5.264"
  ],
  "mix_urls": [
  ],
  "config": {
    "enable_face": true,
    "enable_vehicle": false,
    "jpg_encode_threshold": 300,
    "loop": true,
    "player": 0,
    "upload_url": "http ://localhost:8090/trackupload",
    "decode_result_queue_size": 100,
    "produce": {
      "bg_width": 720,
      "draw_rect_on_bg": true,
      "max_targets_in_track": 3,
      "size_filter_rate": 0.25,
      "remove_vehicle_without_plate": false,
      "feature_count": 1,
      "min_plate_width": 20,
      "plate_binary": true,
      "plate_filter_rate": 0.3,
      "min_plate_bit_score": 0.2,
      "enable_plate": true,
      "enable_vehicle_classify": true,
      "enable_plate_merge": true,
      "enable_portrait": true,
      "vehicle_history_max_duration": 10,
      "vehicle_history_max_size": 20,
      "plate_precision": 2,
      "plate_width": 80,
      "plate_height": 26,
      "max_plate_height": 0.3,
      "stationary_iou_threshold": 0,
      "face_duplicate_threshold": 0.9,
      "face_cluster_threshold": 0.6,
      "face_merge_threshold": 0.7,
      "face_merge_window": 2000,
      "min_face_history_quality": 0.5
    },
    "face": {
      "left": -1,
      "top": -1,
      "width": -1,
      "height": -1,
      "detector_type": 1,
      "detect_interval": 10,
      "track_interval": 2,
      "sample_interval": 2,
      "onet_interval": 3,
      "angle_tb_threshold": 25,
      "angle_lf_threshold": 45,
      "display_margin": 0.5,
      "display_width": 300,
      "enable_display": true,
      "expire_duration": 10000,
      "silent_ttl": 100,
      "max_tracker": 12,
      "min_obj_count": 2,
      "min_width": 14,
      "mtcnn_factor": 0.709,
      "mtcnn_min_size": 30,
      "merge_iou": 0.5,
      "ie_margin_right": 10,
      "ie_margin_bottom": 10,
      "ie_margin_left": 10,
      "ie_margin_top": 10,
      "remove_abnormal_detection": false,
      "horizontal_trip_line": 0,
      "thresh": [
        0.6,
        0.7,
        0.7
      ]
    },
    "vehicle": {
      "left": -1,
      "top": -1,
      "width": -1,
      "height": -1,
      "detect_interval": 2,
      "sample_interval": 8,
      "display_margin": 0.06,
      "display_width": 300,
      "silent_ttl": 480,
      "expire_duration": 10000,
      "max_tracker": 12,
      "min_obj_count": 3,
      "min_width": 14,
      "merge_iou": 0.3,
      "ie_margin_right": 10,
      "ie_margin_bottom": 10,
      "ie_margin_left": 10,
      "ie_margin_top": 0,
      "remove_abnormal_detection": false,
      "horizontal_trip_line": 0,
      "store_ratio": 0.9,
      "activate_station_ratio": 0.7
    },
    "live_height": 270,
    "live_server": 2,
    "live_width": 480
  }
}